{
  "version": "0.4.36",
  "flags": {},
  "shapes": [
    {
      "label": "bl7m_vin_plate",
      "text": "",
      "points": [
        [
          459.0000000000001,
          465.96428571428584
        ],
        [
          1604.7142857142858,
          504.5357142857144
        ],
        [
          1606.142857142857,
          685.9642857142857
        ],
        [
          463.28571428571433,
          643.1071428571429
        ]
      ],
      "group_id": null,
      "shape_type": "polygon",
      "flags": {}
    }
  ],
  "imagePath": "live1.bmp",
  "imageData": null,
  "imageHeight": 1088,
  "imageWidth": 2048
}